batchjax/__init__.py
batchjax/batcher.py
batchjax/core.py
batchjax/looper.py
BatchJAX-0.1.0.dist-info/LICENSE
BatchJAX-0.1.0.dist-info/METADATA
BatchJAX-0.1.0.dist-info/WHEEL
BatchJAX-0.1.0.dist-info/top_level.txt
BatchJAX-0.1.0.dist-info/RECORD
