Metadata-Version: 2.1
Name: BatchJAX
Version: 0.1.0
Summary: Add support for Jax and OBJAX to automatically batch over lists and ModuleLists
Home-page: https://github.com/defaultobject/batchjax
Author: O Hamelijnck
Author-email: ohamelijnck@turing.ac.uk
Classifier: Programming Language :: Python :: 3
Classifier: License :: OSI Approved :: MIT License
Classifier: Operating System :: OS Independent
Requires-Python: >=3.6
License-File: LICENSE
